zoish/__init__.py
zoish/version.py
zoish/abstracs/__init__.py
zoish/abstracs/feature_selector_abstracts.py
zoish/feature_selectors/__init__.py
zoish/feature_selectors/shap_selectors.py
zoish/logs/__init__.py
zoish/utils/__init__.py
zoish/utils/utils.py
zoish-5.0.8.dist-info/licenses/LICENSE
zoish-5.0.8.dist-info/METADATA
zoish-5.0.8.dist-info/WHEEL
zoish-5.0.8.dist-info/top_level.txt
zoish-5.0.8.dist-info/RECORD
