Metadata-Version: 2.4
Name: zoish
Version: 5.0.8
Summary: Zoish streamlines ML with SHAP-based feature selection & interpretability.
Home-page: https://github.com/TorkamaniLab/zoish
Author: drhosseinjavedani
Author-email: h.javedani@gmail.com
License: BSD-3-Clause license
Keywords: Auto ML,Feature Selection,Pipeline,Machine learning,shap
Classifier: Programming Language :: Python :: 3
Classifier: Programming Language :: Python :: 3.8
Classifier: Programming Language :: Python :: 3.9
Classifier: Programming Language :: Python :: 3.10
Classifier: Programming Language :: Python :: 3.11
Classifier: Programming Language :: Python :: 3.12
Classifier: License :: OSI Approved :: BSD License
Classifier: Operating System :: OS Independent
Requires-Python: >=3.8,<3.13
License-File: LICENSE
Requires-Dist: cloudpickle==2.2.1
Requires-Dist: joblib==1.3.2
Requires-Dist: packaging>=23.2
Requires-Dist: psutil<6.1,>=5.9
Requires-Dist: python-dateutil==2.8.2
Requires-Dist: pytz>=2023.3
Requires-Dist: slicer==0.0.7
Requires-Dist: threadpoolctl==3.1.0
Requires-Dist: tqdm==4.66.1
Requires-Dist: six==1.16.0
Requires-Dist: shap==0.42.1
Requires-Dist: matplotlib<3.9,>=3.7
Requires-Dist: importlib-metadata==6.7.0; python_version < "3.10"
Requires-Dist: typing_extensions>=4.13.2; python_version < "3.11"
Requires-Dist: zipp==3.15.0; python_version < "3.10"
Requires-Dist: numpy==1.21.6; python_version < "3.11"
Requires-Dist: pandas==1.3.5; python_version < "3.11"
Requires-Dist: scipy==1.7.3; python_version < "3.11"
Requires-Dist: scikit-learn==1.0.2; python_version < "3.11"
Requires-Dist: numba==0.56.4; python_version < "3.11"
Requires-Dist: llvmlite==0.39.1; python_version < "3.11"
Requires-Dist: fasttreeshap==0.1.6; python_version < "3.11"
Requires-Dist: numpy<2.1,>=1.26; python_version >= "3.11" and python_version < "3.13"
Requires-Dist: pandas<2.2,>=1.5; python_version >= "3.11" and python_version < "3.13"
Requires-Dist: scipy<1.14,>=1.10; python_version >= "3.11" and python_version < "3.13"
Requires-Dist: scikit-learn<1.6,>=1.3; python_version >= "3.11" and python_version < "3.13"
Requires-Dist: numba==0.59.1; python_version >= "3.11" and python_version < "3.13"
Requires-Dist: llvmlite==0.42.0; python_version >= "3.11" and python_version < "3.13"
Requires-Dist: fasttreeshap==0.1.6; python_version >= "3.11" and python_version < "3.13"
Dynamic: author
Dynamic: author-email
Dynamic: classifier
Dynamic: description
Dynamic: description-content-type
Dynamic: home-page
Dynamic: keywords
Dynamic: license
Dynamic: license-file
Dynamic: requires-dist
Dynamic: requires-python
Dynamic: summary
